odus/__init__.py
odus/analysis_utils.py
odus/dacc.py
odus/nothing.py
odus/plot_utils.py
odus/pobj.py
odus/raw_data_diagnosis.py
odus/sequential_var_sets.py
odus/util.py
odus-0.0.8.dist-info/licenses/LICENSE
odus-0.0.8.dist-info/METADATA
odus-0.0.8.dist-info/WHEEL
odus-0.0.8.dist-info/top_level.txt
odus-0.0.8.dist-info/RECORD
