Metadata-Version: 2.4
Name: odus
Version: 0.0.8
Summary: Tools to provide easy access to prepared data to data scientists that cannot be asked.
Home-page: https://github.com/thorwhalen/odus
Author: Thor Whalen
Author-email: thorwhalen1@gmail.com
License: MIT
Keywords: data,data access,drug use,markov,bayesian
Platform: any
License-File: LICENSE
Requires-Dist: py2store
Requires-Dist: pandas
Requires-Dist: numpy
Requires-Dist: Pillow
Requires-Dist: spyn
Requires-Dist: matplotlib
Requires-Dist: openpyxl
Requires-Dist: argh
Dynamic: license-file
